aespm/__init__.py
aespm/experiment.py
aespm/tools.py
aespm/utils.py
aespm-1.1.4.dist-info/METADATA
aespm-1.1.4.dist-info/WHEEL
aespm-1.1.4.dist-info/top_level.txt
aespm-1.1.4.dist-info/RECORD
