Metadata-Version: 2.4
Name: aespm
Version: 1.1.4
Summary: SPM Automation with Python and Machine Learning.
Home-page: https://github.com/RichardLiuCoding/aespm
Download-URL: https://github.com/RichardLiuCoding/aespm.git
Author: ['Richard (Yu) Liu']
License: MIT
Keywords: SPM,Python,Instrument control,Autonomoous,Machine learning,Data Analysis
Classifier: Development Status :: 3 - Alpha
Classifier: Intended Audience :: Developers
Classifier: Topic :: Software Development :: Build Tools
Classifier: License :: OSI Approved :: MIT License
Classifier: Programming Language :: Python :: 3
Requires-Dist: numpy<2.0
Requires-Dist: scipy
Requires-Dist: matplotlib
Requires-Dist: igor2
Requires-Dist: paramiko
Requires-Dist: Pyro5
Dynamic: author
Dynamic: classifier
Dynamic: description
Dynamic: download-url
Dynamic: home-page
Dynamic: keywords
Dynamic: license
Dynamic: requires-dist
Dynamic: summary
